{
    "sound": [
        {
            "stime": 0.0,
            "dur": 1.0,
            "caption": "\nM1 0: others 1: motor_vehicle_road 2: emergency_vehicle 3: siren 4: screaming \n\nM2 0: emergency_vehicle 1: motor_vehicle_road 2: siren 3: others 4: explosion \n\n\nM3 0: emergency_vehicle 1: motor_vehicle_road 2: siren 3: others 4: screaming "
        },
        {
            "stime": 1.0,
            "dur": 1.0,
            "caption": "\nM1 0: others 1: motor_vehicle_road 2: emergency_vehicle 3: siren 4: screaming \n\nM2 0: emergency_vehicle 1: motor_vehicle_road 2: siren 3: others 4: explosion \n\n\nM3 0: emergency_vehicle 1: siren 2: motor_vehicle_road 3: others 4: screaming "
        },
        {
            "stime": 2.0,
            "dur": 1.0,
            "caption": "\nM1 0: others 1: motor_vehicle_road 2: emergency_vehicle 3: siren 4: screaming \n\nM2 0: emergency_vehicle 1: siren 2: motor_vehicle_road 3: others 4: breaking \n\n\nM3 0: emergency_vehicle 1: siren 2: motor_vehicle_road 3: others 4: screaming "
        },
        {
            "stime": 3.0,
            "dur": 1.0,
            "caption": "\nM1 0: motor_vehicle_road 1: others 2: emergency_vehicle 3: crying_sobbing 4: screaming \n\nM2 0: emergency_vehicle 1: siren 2: motor_vehicle_road 3: others 4: breaking \n\n\nM3 0: emergency_vehicle 1: siren 2: motor_vehicle_road 3: others 4: screaming "
        },
        {
            "stime": 4.0,
            "dur": 1.0,
            "caption": "\nM1 0: others 1: motor_vehicle_road 2: emergency_vehicle 3: siren 4: screaming \n\nM2 0: emergency_vehicle 1: siren 2: motor_vehicle_road 3: others 4: explosion \n\n\nM3 0: emergency_vehicle 1: motor_vehicle_road 2: siren 3: others 4: explosion "
        },
        {
            "stime": 5.0,
            "dur": 1.0,
            "caption": "\nM1 0: others 1: motor_vehicle_road 2: emergency_vehicle 3: siren 4: screaming \n\nM2 0: emergency_vehicle 1: motor_vehicle_road 2: siren 3: others 4: explosion \n\n\nM3 0: emergency_vehicle 1: motor_vehicle_road 2: siren 3: others 4: explosion "
        },
        {
            "stime": 6.0,
            "dur": 1.0,
            "caption": "\nM1 0: others 1: motor_vehicle_road 2: emergency_vehicle 3: siren 4: screaming \n\nM2 0: emergency_vehicle 1: motor_vehicle_road 2: siren 3: others 4: explosion \n\n\nM3 0: emergency_vehicle 1: siren 2: motor_vehicle_road 3: others 4: screaming "
        },
        {
            "stime": 7.0,
            "dur": 1.0,
            "caption": "\nM1 0: motor_vehicle_road 1: others 2: crying_sobbing 3: emergency_vehicle 4: screaming \n\nM2 0: emergency_vehicle 1: siren 2: motor_vehicle_road 3: others 4: chatter \n\n\nM3 0: emergency_vehicle 1: siren 2: motor_vehicle_road 3: others 4: screaming "
        },
        {
            "stime": 8.0,
            "dur": 1.0,
            "caption": "\nM1 0: motor_vehicle_road 1: others 2: crying_sobbing 3: emergency_vehicle 4: screaming \n\nM2 0: motor_vehicle_road 1: emergency_vehicle 2: others 3: siren 4: screaming \n\n\nM3 0: motor_vehicle_road 1: emergency_vehicle 2: others 3: siren 4: explosion "
        },
        {
            "stime": 9.0,
            "dur": 1.0,
            "caption": "\nM1 0: others 1: motor_vehicle_road 2: siren 3: emergency_vehicle 4: screaming \n\nM2 0: motor_vehicle_road 1: others 2: emergency_vehicle 3: siren 4: explosion \n\n\nM3 0: motor_vehicle_road 1: others 2: emergency_vehicle 3: siren 4: explosion "
        },
        {
            "stime": 10.0,
            "dur": 1.0,
            "caption": "\nM1 0: motor_vehicle_road 1: others 2: crying_sobbing 3: emergency_vehicle 4: screaming \n\nM2 0: motor_vehicle_road 1: others 2: emergency_vehicle 3: siren 4: explosion \n\n\nM3 0: motor_vehicle_road 1: others 2: emergency_vehicle 3: siren 4: explosion "
        },
        {
            "stime": 11.0,
            "dur": 1.0,
            "caption": "\nM1 0: others 1: motor_vehicle_road 2: emergency_vehicle 3: crying_sobbing 4: screaming \n\nM2 0: motor_vehicle_road 1: others 2: emergency_vehicle 3: siren 4: explosion \n\n\nM3 0: motor_vehicle_road 1: others 2: emergency_vehicle 3: siren 4: explosion "
        },
        {
            "stime": 12.0,
            "dur": 1.0,
            "caption": "\nM1 0: others 1: motor_vehicle_road 2: emergency_vehicle 3: crying_sobbing 4: screaming \n\nM2 0: motor_vehicle_road 1: others 2: emergency_vehicle 3: siren 4: chatter \n\n\nM3 0: motor_vehicle_road 1: others 2: emergency_vehicle 3: siren 4: explosion "
        },
        {
            "stime": 13.0,
            "dur": 1.0,
            "caption": "\nM1 0: others 1: motor_vehicle_road 2: emergency_vehicle 3: crying_sobbing 4: screaming \n\nM2 0: motor_vehicle_road 1: others 2: emergency_vehicle 3: siren 4: explosion \n\n\nM3 0: motor_vehicle_road 1: others 2: emergency_vehicle 3: siren 4: explosion "
        },
        {
            "stime": 14.0,
            "dur": 1.0,
            "caption": "\nM1 0: others 1: motor_vehicle_road 2: emergency_vehicle 3: crying_sobbing 4: screaming \n\nM2 0: motor_vehicle_road 1: others 2: siren 3: emergency_vehicle 4: explosion \n\n\nM3 0: motor_vehicle_road 1: others 2: emergency_vehicle 3: siren 4: explosion "
        },
        {
            "stime": 15.0,
            "dur": 1.0,
            "caption": "\nM1 0: others 1: motor_vehicle_road 2: emergency_vehicle 3: screaming 4: siren \n\nM2 0: motor_vehicle_road 1: others 2: emergency_vehicle 3: siren 4: explosion \n\n\nM3 0: motor_vehicle_road 1: emergency_vehicle 2: others 3: siren 4: explosion "
        },
        {
            "stime": 16.0,
            "dur": 1.0,
            "caption": "\nM1 0: others 1: motor_vehicle_road 2: emergency_vehicle 3: crying_sobbing 4: screaming \n\nM2 0: motor_vehicle_road 1: others 2: emergency_vehicle 3: siren 4: explosion \n\n\nM3 0: emergency_vehicle 1: motor_vehicle_road 2: others 3: siren 4: explosion "
        },
        {
            "stime": 17.0,
            "dur": 1.0,
            "caption": "\nM1 0: others 1: motor_vehicle_road 2: emergency_vehicle 3: crying_sobbing 4: screaming \n\nM2 0: motor_vehicle_road 1: others 2: emergency_vehicle 3: siren 4: screaming \n\n\nM3 0: emergency_vehicle 1: motor_vehicle_road 2: others 3: siren 4: explosion "
        },
        {
            "stime": 18.0,
            "dur": 1.0,
            "caption": "\nM1 0: others 1: motor_vehicle_road 2: siren 3: emergency_vehicle 4: screaming \n\nM2 0: motor_vehicle_road 1: others 2: siren 3: emergency_vehicle 4: chatter \n\n\nM3 0: motor_vehicle_road 1: others 2: emergency_vehicle 3: siren 4: explosion "
        },
        {
            "stime": 19.0,
            "dur": 1.0,
            "caption": "\nM1 0: others 1: motor_vehicle_road 2: siren 3: emergency_vehicle 4: explosion \n\nM2 0: motor_vehicle_road 1: others 2: emergency_vehicle 3: chatter 4: explosion \n\n\nM3 0: motor_vehicle_road 1: others 2: emergency_vehicle 3: explosion 4: siren "
        },
        {
            "stime": 20.0,
            "dur": 1.0,
            "caption": "\nM1 0: others 1: motor_vehicle_road 2: siren 3: emergency_vehicle 4: explosion \n\nM2 0: others 1: motor_vehicle_road 2: siren 3: emergency_vehicle 4: explosion \n\n\nM3 0: motor_vehicle_road 1: others 2: emergency_vehicle 3: explosion 4: siren "
        },
        {
            "stime": 21.0,
            "dur": 1.0,
            "caption": "\nM1 0: others 1: motor_vehicle_road 2: siren 3: emergency_vehicle 4: explosion \n\nM2 0: others 1: motor_vehicle_road 2: siren 3: emergency_vehicle 4: explosion \n\n\nM3 0: others 1: motor_vehicle_road 2: emergency_vehicle 3: gunshot_gunfire 4: explosion "
        },
        {
            "stime": 22.0,
            "dur": 1.0,
            "caption": "\nM1 0: others 1: motor_vehicle_road 2: siren 3: emergency_vehicle 4: explosion \n\nM2 0: others 1: siren 2: motor_vehicle_road 3: emergency_vehicle 4: chatter \n\n\nM3 0: others 1: motor_vehicle_road 2: emergency_vehicle 3: siren 4: explosion "
        },
        {
            "stime": 23.0,
            "dur": 1.0,
            "caption": "\nM1 0: others 1: motor_vehicle_road 2: siren 3: emergency_vehicle 4: explosion \n\nM2 0: others 1: motor_vehicle_road 2: emergency_vehicle 3: siren 4: screaming \n\n\nM3 0: motor_vehicle_road 1: others 2: emergency_vehicle 3: siren 4: explosion "
        },
        {
            "stime": 24.0,
            "dur": 1.0,
            "caption": "\nM1 0: others 1: motor_vehicle_road 2: siren 3: emergency_vehicle 4: explosion \n\nM2 0: motor_vehicle_road 1: others 2: emergency_vehicle 3: explosion 4: chatter \n\n\nM3 0: motor_vehicle_road 1: others 2: emergency_vehicle 3: siren 4: explosion "
        },
        {
            "stime": 25.0,
            "dur": 1.0,
            "caption": "\nM1 0: others 1: motor_vehicle_road 2: siren 3: emergency_vehicle 4: screaming \n\nM2 0: motor_vehicle_road 1: emergency_vehicle 2: others 3: siren 4: explosion \n\n\nM3 0: motor_vehicle_road 1: others 2: emergency_vehicle 3: explosion 4: siren "
        },
        {
            "stime": 26.0,
            "dur": 1.0,
            "caption": "\nM1 0: others 1: motor_vehicle_road 2: emergency_vehicle 3: siren 4: screaming \n\nM2 0: others 1: motor_vehicle_road 2: emergency_vehicle 3: siren 4: chatter \n\n\nM3 0: motor_vehicle_road 1: others 2: emergency_vehicle 3: siren 4: explosion "
        },
        {
            "stime": 27.0,
            "dur": 1.0,
            "caption": "\nM1 0: others 1: motor_vehicle_road 2: siren 3: emergency_vehicle 4: explosion \n\nM2 0: emergency_vehicle 1: siren 2: motor_vehicle_road 3: others 4: screaming \n\n\nM3 0: motor_vehicle_road 1: emergency_vehicle 2: others 3: siren 4: explosion "
        },
        {
            "stime": 28.0,
            "dur": 1.0,
            "caption": "\nM1 0: others 1: motor_vehicle_road 2: siren 3: emergency_vehicle 4: explosion \n\nM2 0: emergency_vehicle 1: motor_vehicle_road 2: others 3: siren 4: explosion \n\n\nM3 0: motor_vehicle_road 1: others 2: emergency_vehicle 3: siren 4: explosion "
        },
        {
            "stime": 29.0,
            "dur": 1.0,
            "caption": "\nM1 0: others 1: motor_vehicle_road 2: siren 3: emergency_vehicle 4: screaming \n\nM2 0: emergency_vehicle 1: motor_vehicle_road 2: others 3: siren 4: explosion \n\n\nM3 0: motor_vehicle_road 1: others 2: emergency_vehicle 3: siren 4: explosion "
        },
        {
            "stime": 30.0,
            "dur": 1.0,
            "caption": "\nM1 0: others 1: motor_vehicle_road 2: siren 3: emergency_vehicle 4: screaming \n\nM2 0: motor_vehicle_road 1: others 2: emergency_vehicle 3: explosion 4: siren \n\n\nM3 0: motor_vehicle_road 1: others 2: emergency_vehicle 3: siren 4: explosion "
        },
        {
            "stime": 31.0,
            "dur": 1.0,
            "caption": "\nM1 0: others 1: motor_vehicle_road 2: emergency_vehicle 3: crying_sobbing 4: screaming \n\nM2 0: motor_vehicle_road 1: others 2: emergency_vehicle 3: siren 4: explosion \n\n\nM3 0: motor_vehicle_road 1: others 2: emergency_vehicle 3: siren 4: explosion "
        },
        {
            "stime": 32.0,
            "dur": 1.0,
            "caption": "\nM1 0: others 1: motor_vehicle_road 2: siren 3: emergency_vehicle 4: explosion \n\nM2 0: motor_vehicle_road 1: others 2: siren 3: emergency_vehicle 4: explosion \n\n\nM3 0: others 1: motor_vehicle_road 2: emergency_vehicle 3: gunshot_gunfire 4: siren "
        },
        {
            "stime": 33.0,
            "dur": 1.0,
            "caption": "\nM1 0: others 1: motor_vehicle_road 2: siren 3: emergency_vehicle 4: explosion \n\nM2 0: motor_vehicle_road 1: others 2: siren 3: emergency_vehicle 4: explosion \n\n\nM3 0: motor_vehicle_road 1: others 2: emergency_vehicle 3: siren 4: explosion "
        },
        {
            "stime": 34.0,
            "dur": 1.0,
            "caption": "\nM1 0: others 1: motor_vehicle_road 2: emergency_vehicle 3: siren 4: screaming \n\nM2 0: motor_vehicle_road 1: others 2: emergency_vehicle 3: siren 4: explosion \n\n\nM3 0: motor_vehicle_road 1: others 2: emergency_vehicle 3: explosion 4: siren "
        },
        {
            "stime": 35.0,
            "dur": 1.0,
            "caption": "\nM1 0: others 1: motor_vehicle_road 2: emergency_vehicle 3: screaming 4: crying_sobbing \n\nM2 0: others 1: motor_vehicle_road 2: emergency_vehicle 3: siren 4: explosion \n\n\nM3 0: motor_vehicle_road 1: others 2: emergency_vehicle 3: explosion 4: siren "
        },
        {
            "stime": 36.0,
            "dur": 1.0,
            "caption": "\nM1 0: others 1: motor_vehicle_road 2: siren 3: emergency_vehicle 4: screaming \n\nM2 0: motor_vehicle_road 1: others 2: siren 3: emergency_vehicle 4: explosion \n\n\nM3 0: motor_vehicle_road 1: others 2: emergency_vehicle 3: siren 4: explosion "
        },
        {
            "stime": 37.0,
            "dur": 1.0,
            "caption": "\nM1 0: others 1: motor_vehicle_road 2: siren 3: emergency_vehicle 4: explosion \n\nM2 0: motor_vehicle_road 1: others 2: siren 3: emergency_vehicle 4: explosion \n\n\nM3 0: motor_vehicle_road 1: others 2: emergency_vehicle 3: siren 4: explosion "
        },
        {
            "stime": 38.0,
            "dur": 1.0,
            "caption": "\nM1 0: others 1: motor_vehicle_road 2: siren 3: emergency_vehicle 4: explosion \n\nM2 0: others 1: motor_vehicle_road 2: siren 3: emergency_vehicle 4: explosion \n\n\nM3 0: motor_vehicle_road 1: others 2: emergency_vehicle 3: siren 4: explosion "
        },
        {
            "stime": 39.0,
            "dur": 1.0,
            "caption": "\nM1 0: others 1: motor_vehicle_road 2: siren 3: emergency_vehicle 4: explosion \n\nM2 0: others 1: motor_vehicle_road 2: siren 3: emergency_vehicle 4: explosion \n\n\nM3 0: motor_vehicle_road 1: others 2: emergency_vehicle 3: explosion 4: siren "
        },
        {
            "stime": 40.0,
            "dur": 1.0,
            "caption": "\nM1 0: others 1: motor_vehicle_road 2: siren 3: emergency_vehicle 4: explosion \n\nM2 0: others 1: motor_vehicle_road 2: siren 3: emergency_vehicle 4: explosion \n\n\nM3 0: motor_vehicle_road 1: others 2: emergency_vehicle 3: explosion 4: gunshot_gunfire "
        },
        {
            "stime": 41.0,
            "dur": 1.0,
            "caption": "\nM1 0: others 1: motor_vehicle_road 2: siren 3: emergency_vehicle 4: explosion \n\nM2 0: motor_vehicle_road 1: others 2: explosion 3: emergency_vehicle 4: siren \n\n\nM3 0: motor_vehicle_road 1: others 2: emergency_vehicle 3: explosion 4: siren "
        },
        {
            "stime": 42.0,
            "dur": 1.0,
            "caption": "\nM1 0: others 1: motor_vehicle_road 2: siren 3: emergency_vehicle 4: explosion \n\nM2 0: motor_vehicle_road 1: others 2: siren 3: emergency_vehicle 4: explosion \n\n\nM3 0: motor_vehicle_road 1: others 2: emergency_vehicle 3: explosion 4: siren "
        },
        {
            "stime": 43.0,
            "dur": 1.0,
            "caption": "\nM1 0: others 1: motor_vehicle_road 2: siren 3: emergency_vehicle 4: explosion \n\nM2 0: motor_vehicle_road 1: others 2: siren 3: emergency_vehicle 4: explosion \n\n\nM3 0: others 1: motor_vehicle_road 2: emergency_vehicle 3: siren 4: explosion "
        },
        {
            "stime": 44.0,
            "dur": 1.0,
            "caption": "\nM1 0: others 1: motor_vehicle_road 2: siren 3: emergency_vehicle 4: explosion \n\nM2 0: motor_vehicle_road 1: others 2: siren 3: emergency_vehicle 4: explosion \n\n\nM3 0: others 1: motor_vehicle_road 2: siren 3: gunshot_gunfire 4: emergency_vehicle "
        },
        {
            "stime": 45.0,
            "dur": 1.0,
            "caption": "\nM1 0: others 1: motor_vehicle_road 2: crying_sobbing 3: emergency_vehicle 4: screaming \n\nM2 0: others 1: motor_vehicle_road 2: siren 3: emergency_vehicle 4: explosion \n\n\nM3 0: others 1: motor_vehicle_road 2: explosion 3: gunshot_gunfire 4: emergency_vehicle "
        },
        {
            "stime": 46.0,
            "dur": 1.0,
            "caption": "\nM1 0: others 1: motor_vehicle_road 2: siren 3: emergency_vehicle 4: screaming \n\nM2 0: others 1: motor_vehicle_road 2: siren 3: emergency_vehicle 4: explosion \n\n\nM3 0: others 1: motor_vehicle_road 2: explosion 3: gunshot_gunfire 4: emergency_vehicle "
        },
        {
            "stime": 47.0,
            "dur": 1.0,
            "caption": "\nM1 0: others 1: motor_vehicle_road 2: siren 3: emergency_vehicle 4: screaming \n\nM2 0: motor_vehicle_road 1: others 2: siren 3: explosion 4: emergency_vehicle \n\n\nM3 0: others 1: motor_vehicle_road 2: explosion 3: emergency_vehicle 4: gunshot_gunfire "
        },
        {
            "stime": 48.0,
            "dur": 1.0,
            "caption": "\nM1 0: others 1: motor_vehicle_road 2: siren 3: emergency_vehicle 4: explosion \n\nM2 0: motor_vehicle_road 1: others 2: siren 3: emergency_vehicle 4: explosion \n\n\nM3 0: others 1: motor_vehicle_road 2: emergency_vehicle 3: siren 4: explosion "
        },
        {
            "stime": 49.0,
            "dur": 1.0,
            "caption": "\nM1 0: others 1: motor_vehicle_road 2: siren 3: emergency_vehicle 4: screaming \n\nM2 0: motor_vehicle_road 1: others 2: siren 3: emergency_vehicle 4: explosion \n\n\nM3 0: emergency_vehicle 1: motor_vehicle_road 2: others 3: siren 4: explosion "
        },
        {
            "stime": 50.0,
            "dur": 1.0,
            "caption": "\nM1 0: others 1: motor_vehicle_road 2: crying_sobbing 3: emergency_vehicle 4: screaming \n\nM2 0: motor_vehicle_road 1: others 2: emergency_vehicle 3: siren 4: explosion \n\n\nM3 0: emergency_vehicle 1: motor_vehicle_road 2: others 3: siren 4: explosion "
        },
        {
            "stime": 51.0,
            "dur": 1.0,
            "caption": "\nM1 0: others 1: motor_vehicle_road 2: emergency_vehicle 3: crying_sobbing 4: screaming \n\nM2 0: motor_vehicle_road 1: others 2: siren 3: emergency_vehicle 4: explosion \n\n\nM3 0: emergency_vehicle 1: motor_vehicle_road 2: others 3: siren 4: explosion "
        },
        {
            "stime": 52.0,
            "dur": 1.0,
            "caption": "\nM1 0: others 1: motor_vehicle_road 2: siren 3: emergency_vehicle 4: screaming \n\nM2 0: motor_vehicle_road 1: others 2: emergency_vehicle 3: siren 4: explosion \n\n\nM3 0: motor_vehicle_road 1: others 2: emergency_vehicle 3: siren 4: explosion "
        },
        {
            "stime": 53.0,
            "dur": 1.0,
            "caption": "\nM1 0: others 1: motor_vehicle_road 2: siren 3: emergency_vehicle 4: explosion \n\nM2 0: motor_vehicle_road 1: others 2: siren 3: emergency_vehicle 4: explosion \n\n\nM3 0: motor_vehicle_road 1: others 2: emergency_vehicle 3: siren 4: explosion "
        },
        {
            "stime": 54.0,
            "dur": 1.0,
            "caption": "\nM1 0: others 1: motor_vehicle_road 2: siren 3: emergency_vehicle 4: explosion \n\nM2 0: motor_vehicle_road 1: others 2: siren 3: emergency_vehicle 4: explosion \n\n\nM3 0: motor_vehicle_road 1: others 2: emergency_vehicle 3: siren 4: explosion "
        },
        {
            "stime": 55.0,
            "dur": 1.0,
            "caption": "\nM1 0: others 1: motor_vehicle_road 2: siren 3: emergency_vehicle 4: explosion \n\nM2 0: motor_vehicle_road 1: others 2: siren 3: emergency_vehicle 4: explosion \n\n\nM3 0: motor_vehicle_road 1: others 2: emergency_vehicle 3: siren 4: explosion "
        },
        {
            "stime": 56.0,
            "dur": 1.0,
            "caption": "\nM1 0: others 1: motor_vehicle_road 2: siren 3: emergency_vehicle 4: explosion \n\nM2 0: motor_vehicle_road 1: others 2: siren 3: emergency_vehicle 4: explosion \n\n\nM3 0: motor_vehicle_road 1: others 2: emergency_vehicle 3: siren 4: explosion "
        },
        {
            "stime": 57.0,
            "dur": 1.0,
            "caption": "\nM1 0: others 1: motor_vehicle_road 2: siren 3: emergency_vehicle 4: explosion \n\nM2 0: motor_vehicle_road 1: others 2: emergency_vehicle 3: siren 4: explosion \n\n\nM3 0: motor_vehicle_road 1: emergency_vehicle 2: others 3: siren 4: explosion "
        },
        {
            "stime": 58.0,
            "dur": 1.0,
            "caption": "\nM1 0: others 1: motor_vehicle_road 2: siren 3: emergency_vehicle 4: explosion \n\nM2 0: motor_vehicle_road 1: others 2: emergency_vehicle 3: siren 4: explosion \n\n\nM3 0: motor_vehicle_road 1: others 2: emergency_vehicle 3: siren 4: explosion "
        },
        {
            "stime": 59.0,
            "dur": 1.0,
            "caption": "\nM1 0: others 1: motor_vehicle_road 2: siren 3: emergency_vehicle 4: explosion \n\nM2 0: others 1: motor_vehicle_road 2: emergency_vehicle 3: siren 4: explosion \n\n\nM3 0: others 1: motor_vehicle_road 2: emergency_vehicle 3: siren 4: gunshot_gunfire "
        },
        {
            "stime": 60.0,
            "dur": 1.0,
            "caption": "\nM1 0: others 1: motor_vehicle_road 2: siren 3: emergency_vehicle 4: explosion \n\nM2 0: motor_vehicle_road 1: others 2: emergency_vehicle 3: siren 4: explosion \n\n\nM3 0: motor_vehicle_road 1: others 2: emergency_vehicle 3: gunshot_gunfire 4: siren "
        },
        {
            "stime": 61.0,
            "dur": 1.0,
            "caption": "\nM1 0: others 1: motor_vehicle_road 2: emergency_vehicle 3: screaming 4: crying_sobbing \n\nM2 0: motor_vehicle_road 1: others 2: emergency_vehicle 3: siren 4: explosion \n\n\nM3 0: motor_vehicle_road 1: others 2: emergency_vehicle 3: explosion 4: siren "
        },
        {
            "stime": 62.0,
            "dur": 1.0,
            "caption": "\nM1 0: others 1: motor_vehicle_road 2: siren 3: emergency_vehicle 4: explosion \n\nM2 0: motor_vehicle_road 1: others 2: emergency_vehicle 3: siren 4: explosion \n\n\nM3 0: motor_vehicle_road 1: others 2: emergency_vehicle 3: siren 4: explosion "
        },
        {
            "stime": 63.0,
            "dur": 1.0,
            "caption": "\nM1 0: others 1: motor_vehicle_road 2: emergency_vehicle 3: siren 4: screaming \n\nM2 0: motor_vehicle_road 1: others 2: explosion 3: siren 4: emergency_vehicle \n\n\nM3 0: others 1: motor_vehicle_road 2: emergency_vehicle 3: siren 4: explosion "
        },
        {
            "stime": 64.0,
            "dur": 1.0,
            "caption": "\nM1 0: others 1: motor_vehicle_road 2: emergency_vehicle 3: siren 4: explosion \n\nM2 0: motor_vehicle_road 1: others 2: explosion 3: siren 4: emergency_vehicle \n\n\nM3 0: others 1: motor_vehicle_road 2: emergency_vehicle 3: siren 4: explosion "
        },
        {
            "stime": 65.0,
            "dur": 1.0,
            "caption": "\nM1 0: others 1: motor_vehicle_road 2: emergency_vehicle 3: siren 4: screaming \n\nM2 0: motor_vehicle_road 1: others 2: siren 3: emergency_vehicle 4: explosion \n\n\nM3 0: motor_vehicle_road 1: others 2: emergency_vehicle 3: siren 4: explosion "
        },
        {
            "stime": 66.0,
            "dur": 1.0,
            "caption": "\nM1 0: others 1: motor_vehicle_road 2: siren 3: emergency_vehicle 4: screaming \n\nM2 0: others 1: motor_vehicle_road 2: siren 3: explosion 4: emergency_vehicle \n\n\nM3 0: motor_vehicle_road 1: others 2: emergency_vehicle 3: siren 4: explosion "
        },
        {
            "stime": 67.0,
            "dur": 1.0,
            "caption": "\nM1 0: others 1: motor_vehicle_road 2: siren 3: emergency_vehicle 4: screaming \n\nM2 0: others 1: motor_vehicle_road 2: siren 3: emergency_vehicle 4: explosion \n\n\nM3 0: motor_vehicle_road 1: others 2: emergency_vehicle 3: explosion 4: siren "
        },
        {
            "stime": 68.0,
            "dur": 1.0,
            "caption": "\nM1 0: others 1: motor_vehicle_road 2: emergency_vehicle 3: screaming 4: crying_sobbing \n\nM2 0: others 1: motor_vehicle_road 2: siren 3: emergency_vehicle 4: explosion \n\n\nM3 0: motor_vehicle_road 1: others 2: emergency_vehicle 3: explosion 4: siren "
        },
        {
            "stime": 69.0,
            "dur": 1.0,
            "caption": "\nM1 0: others 1: motor_vehicle_road 2: siren 3: emergency_vehicle 4: explosion \n\nM2 0: motor_vehicle_road 1: others 2: siren 3: emergency_vehicle 4: explosion \n\n\nM3 0: motor_vehicle_road 1: others 2: emergency_vehicle 3: siren 4: explosion "
        },
        {
            "stime": 70.0,
            "dur": 1.0,
            "caption": "\nM1 0: others 1: motor_vehicle_road 2: siren 3: emergency_vehicle 4: explosion \n\nM2 0: others 1: motor_vehicle_road 2: siren 3: emergency_vehicle 4: explosion \n\n\nM3 0: motor_vehicle_road 1: emergency_vehicle 2: others 3: siren 4: explosion "
        },
        {
            "stime": 71.0,
            "dur": 1.0,
            "caption": "\nM1 0: others 1: motor_vehicle_road 2: siren 3: emergency_vehicle 4: explosion \n\nM2 0: others 1: motor_vehicle_road 2: siren 3: emergency_vehicle 4: chatter \n\n\nM3 0: emergency_vehicle 1: others 2: motor_vehicle_road 3: siren 4: explosion "
        },
        {
            "stime": 72.0,
            "dur": 1.0,
            "caption": "\nM1 0: others 1: motor_vehicle_road 2: siren 3: emergency_vehicle 4: explosion \n\nM2 0: others 1: motor_vehicle_road 2: siren 3: emergency_vehicle 4: chatter \n\n\nM3 0: emergency_vehicle 1: others 2: motor_vehicle_road 3: siren 4: explosion "
        },
        {
            "stime": 73.0,
            "dur": 1.0,
            "caption": "\nM1 0: others 1: motor_vehicle_road 2: siren 3: emergency_vehicle 4: explosion \n\nM2 0: others 1: motor_vehicle_road 2: siren 3: emergency_vehicle 4: chatter \n\n\nM3 0: others 1: motor_vehicle_road 2: emergency_vehicle 3: siren 4: gunshot_gunfire "
        },
        {
            "stime": 74.0,
            "dur": 1.0,
            "caption": "\nM1 0: others 1: motor_vehicle_road 2: siren 3: emergency_vehicle 4: explosion \n\nM2 0: siren 1: others 2: motor_vehicle_road 3: emergency_vehicle 4: explosion \n\n\nM3 0: others 1: motor_vehicle_road 2: emergency_vehicle 3: siren 4: gunshot_gunfire "
        },
        {
            "stime": 75.0,
            "dur": 1.0,
            "caption": "\nM1 0: others 1: motor_vehicle_road 2: siren 3: emergency_vehicle 4: explosion \n\nM2 0: siren 1: others 2: emergency_vehicle 3: motor_vehicle_road 4: chatter \n\n\nM3 0: emergency_vehicle 1: others 2: siren 3: motor_vehicle_road 4: gunshot_gunfire "
        },
        {
            "stime": 76.0,
            "dur": 1.0,
            "caption": "\nM1 0: others 1: motor_vehicle_road 2: siren 3: emergency_vehicle 4: screaming \n\nM2 0: others 1: siren 2: motor_vehicle_road 3: emergency_vehicle 4: explosion \n\n\nM3 0: others 1: emergency_vehicle 2: siren 3: motor_vehicle_road 4: gunshot_gunfire "
        },
        {
            "stime": 77.0,
            "dur": 1.0,
            "caption": "\nM1 0: others 1: motor_vehicle_road 2: siren 3: emergency_vehicle 4: screaming \n\nM2 0: others 1: siren 2: motor_vehicle_road 3: emergency_vehicle 4: explosion \n\n\nM3 0: others 1: siren 2: motor_vehicle_road 3: emergency_vehicle 4: gunshot_gunfire "
        },
        {
            "stime": 78.0,
            "dur": 1.0,
            "caption": "\nM1 0: others 1: motor_vehicle_road 2: siren 3: emergency_vehicle 4: screaming \n\nM2 0: others 1: siren 2: motor_vehicle_road 3: emergency_vehicle 4: explosion \n\n\nM3 0: others 1: motor_vehicle_road 2: siren 3: gunshot_gunfire 4: emergency_vehicle "
        },
        {
            "stime": 79.0,
            "dur": 1.0,
            "caption": "\nM1 0: others 1: motor_vehicle_road 2: siren 3: emergency_vehicle 4: screaming \n\nM2 0: others 1: motor_vehicle_road 2: siren 3: emergency_vehicle 4: explosion \n\n\nM3 0: others 1: motor_vehicle_road 2: siren 3: gunshot_gunfire 4: emergency_vehicle "
        },
        {
            "stime": 80.0,
            "dur": 1.0,
            "caption": "\nM1 0: others 1: motor_vehicle_road 2: siren 3: screaming 4: emergency_vehicle \n\nM2 0: others 1: motor_vehicle_road 2: chatter 3: emergency_vehicle 4: siren \n\n\nM3 0: others 1: motor_vehicle_road 2: emergency_vehicle 3: siren 4: gunshot_gunfire "
        },
        {
            "stime": 81.0,
            "dur": 1.0,
            "caption": "\nM1 0: others 1: motor_vehicle_road 2: siren 3: emergency_vehicle 4: screaming \n\nM2 0: siren 1: others 2: emergency_vehicle 3: motor_vehicle_road 4: gunshot_gunfire \n\n\nM3 0: others 1: siren 2: motor_vehicle_road 3: emergency_vehicle 4: gunshot_gunfire "
        },
        {
            "stime": 82.0,
            "dur": 1.0,
            "caption": "\nM1 0: others 1: motor_vehicle_road 2: siren 3: emergency_vehicle 4: screaming \n\nM2 0: siren 1: others 2: motor_vehicle_road 3: emergency_vehicle 4: explosion \n\n\nM3 0: others 1: siren 2: motor_vehicle_road 3: emergency_vehicle 4: gunshot_gunfire "
        },
        {
            "stime": 83.0,
            "dur": 1.0,
            "caption": "\nM1 0: others 1: motor_vehicle_road 2: siren 3: emergency_vehicle 4: explosion \n\nM2 0: siren 1: others 2: motor_vehicle_road 3: emergency_vehicle 4: explosion \n\n\nM3 0: others 1: siren 2: motor_vehicle_road 3: emergency_vehicle 4: gunshot_gunfire "
        },
        {
            "stime": 84.0,
            "dur": 1.0,
            "caption": "\nM1 0: others 1: motor_vehicle_road 2: siren 3: emergency_vehicle 4: screaming \n\nM2 0: siren 1: others 2: motor_vehicle_road 3: explosion 4: gunshot_gunfire \n\n\nM3 0: others 1: motor_vehicle_road 2: gunshot_gunfire 3: explosion 4: siren "
        },
        {
            "stime": 85.0,
            "dur": 1.0,
            "caption": "\nM1 0: others 1: motor_vehicle_road 2: siren 3: screaming 4: explosion \n\nM2 0: others 1: siren 2: explosion 3: motor_vehicle_road 4: emergency_vehicle \n\n\nM3 0: others 1: motor_vehicle_road 2: gunshot_gunfire 3: explosion 4: emergency_vehicle "
        },
        {
            "stime": 86.0,
            "dur": 1.0,
            "caption": "\nM1 0: others 1: motor_vehicle_road 2: siren 3: screaming 4: gunshot_gunfire \n\nM2 0: explosion 1: emergency_vehicle 2: siren 3: others 4: motor_vehicle_road \n\nM3 0: explosion 1: motor_vehicle_road 2: others 3: gunshot_gunfire 4: breaking "
        }
    ]
}